MANIFEST.in
README.txt
requirements.txt
setup.py
test_requirements.txt
version.txt
cloudshell/__init__.py
cloudshell/networking/__init__.py
cloudshell/networking/cisco/__init__.py
cloudshell/networking/cisco/ios/__init__.py
cloudshell/networking/cisco/ios/autoload/__init__.py
cloudshell/networking/cisco/ios/autoload/autoload_structure.py
cloudshell/networking/cisco/ios/autoload/cisco_autoload_runner.py
cloudshell/networking/cisco/ios/autoload/cisco_ios_autoload.py
cloudshell/tests/__init__.py
cloudshell_networking_cisco_ios.egg-info/PKG-INFO
cloudshell_networking_cisco_ios.egg-info/SOURCES.txt
cloudshell_networking_cisco_ios.egg-info/dependency_links.txt
cloudshell_networking_cisco_ios.egg-info/requires.txt
cloudshell_networking_cisco_ios.egg-info/top_level.txt