Metadata-Version: 1.0
Name: cloudshell-networking-cisco-ios
Version: 4.0.187
Summary: QualiSystems networking cisco IOS specific Package
Home-page: http://www.qualisystems.com/
Author: QualiSystems
Author-email: info@qualisystems.com
License: UNKNOWN
Platform: UNKNOWN
